aea_cli_ipfs/__init__.py
aea_cli_ipfs/core.py
aea_cli_ipfs/exceptions.py
aea_cli_ipfs/ipfs_utils.py
aea_cli_ipfs/py.typed
aea_cli_ipfs/registry.py
open_aea_cli_ipfs-2.0.8.dist-info/licenses/LICENSE
open_aea_cli_ipfs-2.0.8.dist-info/METADATA
open_aea_cli_ipfs-2.0.8.dist-info/WHEEL
open_aea_cli_ipfs-2.0.8.dist-info/entry_points.txt
open_aea_cli_ipfs-2.0.8.dist-info/top_level.txt
open_aea_cli_ipfs-2.0.8.dist-info/RECORD
